cyclic_lamp.v
module cyclic_lamp(clock, light);

input clock;
output reg [0:2] light;
parameter s0=0, s1=1, s2=2;
parameter red= 3'b100, green= 3'b010, yellow= 3'b001;
reg [0:1] state;

always @(posedge clock)

case (state)
	s0: 
	begin
		light <= green;
		state <= s1;
	end

	s1: 
	begin
		light <= yellow;
		state <= s2;
	end

	s2: 
	begin
		light <= red;
		state <= s0;
	end

	default:
	begin
		light <= red;
		state <= s1;
	end

endcase

endmodule

cyclic_lamp_tb.v
module test_cyclic_lamp;

reg clk;
wire [0:2] light;

cyclic_lamp DUT (clk, light);

always #5 clk= ~clk;
	initial
   	begin 

	clk=0;
	#100 $finish;

	end

	initial 
	begin

	$dumpfile ("cyclic.vcd");
	$dumpvars (0, test_cyclic_lamp);
	$monitor ($time, "RGY: %b", light);

   	end

endmodule

cyclic.vcd
$date
    Sep  8, 2023  19:05:56
$end
$version
    TOOL:	xmsim(64)	20.09-s012
$end
$timescale
    1 ns
$end

$scope module test_cyclic_lamp $end
$var reg       1 !    clk $end
$var wire      3 "    light [0:2] $end

$scope module DUT $end
$var wire      1 #    clock  $end
$var reg       3 $    light [0:2] $end
$var parameter 32 %    s0 $end
$var parameter 32 &    s1 $end
$var parameter 32 '    s2 $end
$var parameter  3 (    red $end
$var parameter  3 )    green $end
$var parameter  3 *    yellow $end
$var reg       2 +    state [0:1] $end
$upscope $end

$upscope $end

$enddefinitions $end
$dumpvars
b1 *
b10 )
b100 (
b10 '
b1 &
b0 %
0!
bx "
0#
bx $
bx +
$end
#5
1!
1#
b100 $
b1 +
b100 "
#10
0!
0#
#15
1!
1#
b1 $
b10 +
b1 "
#20
0!
0#
#25
1!
1#
b100 $
b0 +
b100 "
#30
0!
0#
#35
1!
1#
b10 $
b1 +
b10 "
#40
0!
0#
#45
1!
1#
b1 $
b10 +
b1 "
#50
0!
0#
#55
1!
1#
b100 $
b0 +
b100 "
#60
0!
0#
#65
1!
1#
b10 $
b1 +
b10 "
#70
0!
0#
#75
1!
1#
b1 $
b10 +
b1 "
#80
0!
0#
#85
1!
1#
b100 $
b0 +
b100 "
#90
0!
0#
#95
1!
1#
b10 $
b1 +
b10 "
